setup.py
PythonEggTools.egg-info/PKG-INFO
PythonEggTools.egg-info/SOURCES.txt
PythonEggTools.egg-info/dependency_links.txt
PythonEggTools.egg-info/entry_points.txt
PythonEggTools.egg-info/top_level.txt
pet/__init__.py
pet/fillparagraph.py
pet/petcache.py
pet/petget.py
