Metadata-Version: 1.0
Name: PythonEggTools
Version: 1.0a0
Summary: Command line tools for working with Python packages
Home-page: UNKNOWN
Author: Maris Fogels
Author-email: mfogels@interactdirect.com
License: BSD
Platform: UNKNOWN
Classifier: Development Status :: 3 - Alpha
Classifier: Environment :: Console
Classifier: Intended Audience :: End Users/Desktop
Classifier: Intended Audience :: Developers
Classifier: Intended Audience :: System Administrators
Classifier: Operating System :: OS Independent
Classifier: Topic :: Utilities
Classifier: Topic :: System :: Systems Administration
Classifier: Programming Language :: Python
